MANIFEST.in
Readme.md
dev-requirements.frozen.txt
dev-requirements.txt
licence.txt
noxfile.py
requirements.frozen.txt
requirements.txt
setup.cfg
setup.py
pandas_ml_quant/__init__.py
pandas_ml_quant/empirical.py
pandas_ml_quant/utils.py
pandas_ml_quant.egg-info/PKG-INFO
pandas_ml_quant.egg-info/SOURCES.txt
pandas_ml_quant.egg-info/dependency_links.txt
pandas_ml_quant.egg-info/requires.txt
pandas_ml_quant.egg-info/top_level.txt
pandas_ml_quant/__pycache__/__init__.cpython-37.pyc
pandas_ml_quant/__pycache__/__init__.cpython-38.pyc
pandas_ml_quant/__pycache__/empirical.cpython-38.pyc
pandas_ml_quant/__pycache__/utils.cpython-38.pyc
pandas_ml_quant/model/__init__.py
pandas_ml_quant/model/__pycache__/__init__.cpython-37.pyc
pandas_ml_quant/model/__pycache__/__init__.cpython-38.pyc
pandas_ml_quant/model/cross_validation/__init__.py
pandas_ml_quant/model/cross_validation/rolling_window_cv.py
pandas_ml_quant/model/cross_validation/__pycache__/__init__.cpython-37.pyc
pandas_ml_quant/model/cross_validation/__pycache__/__init__.cpython-38.pyc
pandas_ml_quant/model/cross_validation/__pycache__/rolling_window_cv.cpython-37.pyc
pandas_ml_quant/model/cross_validation/__pycache__/rolling_window_cv.cpython-38.pyc
pandas_ml_quant/model/forecast/__init__.py
pandas_ml_quant/model/forecast/distribution_forecast.py
pandas_ml_quant/model/forecast/__pycache__/__init__.cpython-38.pyc
pandas_ml_quant/model/forecast/__pycache__/distribution_forecast.cpython-38.pyc
pandas_ml_quant/model/summary/__init__.py
pandas_ml_quant/model/summary/_utils.py
pandas_ml_quant/model/summary/binary_weighted_classification_summary.py
pandas_ml_quant/model/summary/portfolio_weights_summary.py
pandas_ml_quant/model/summary/price_prediction_summary.py
pandas_ml_quant/model/summary/weighted_classification_summary.py
pandas_ml_quant/model/summary/__pycache__/__init__.cpython-37.pyc
pandas_ml_quant/model/summary/__pycache__/__init__.cpython-38.pyc
pandas_ml_quant/model/summary/__pycache__/_utils.cpython-38.pyc
pandas_ml_quant/model/summary/__pycache__/binary_weighted_classification_summary.cpython-37.pyc
pandas_ml_quant/model/summary/__pycache__/binary_weighted_classification_summary.cpython-38.pyc
